project/__init__.py
project/functions.py
project/init.py
project/nacos_client.py
project/operations.py
project/routes.py
project/server.py
project/YoloV5Detector/V5Detector.py
project/YoloV5Detector/__init__.py
project/models/__init__.py
project/models/common.py
project/models/experimental.py
project/models/yolo.py
project/utils/__init__.py
project/utils/activations.py
project/utils/augmentations.py
project/utils/autoanchor.py
project/utils/datasets.py
project/utils/downloads.py
project/utils/general.py
project/utils/google_utils.py
project/utils/metrics.py
project/utils/plots.py
project/utils/torch_utils.py
ng_fruitdetect-1.0.0.dist-info/METADATA
ng_fruitdetect-1.0.0.dist-info/WHEEL
ng_fruitdetect-1.0.0.dist-info/entry_points.txt
ng_fruitdetect-1.0.0.dist-info/top_level.txt
ng_fruitdetect-1.0.0.dist-info/RECORD
